huailib/__init__.py
huailib/algorithms.py
huailib/collections.py
huailib-0.0.2.dist-info/METADATA
huailib-0.0.2.dist-info/WHEEL
huailib-0.0.2.dist-info/top_level.txt
huailib-0.0.2.dist-info/RECORD
