Metadata-Version: 2.1
Name: huailib
Version: 0.0.2
Summary: a helpful python library
Home-page: https://github.com/wsmgh/hpl.git
Author: huai guo
Author-email: guohuai@csu.edu.cn
